NLFE/__init__.py
NLFE/nlfe.py
NLFE-0.0.1.dist-info/LICENSE
NLFE-0.0.1.dist-info/METADATA
NLFE-0.0.1.dist-info/WHEEL
NLFE-0.0.1.dist-info/top_level.txt
NLFE-0.0.1.dist-info/RECORD
